osm_changeset_brain/__init__.py
osm_changeset_brain/lorem_ipsum.py
osm_changeset_brain-0.0.1.dist-info/licenses/LICENSE
osm_changeset_brain-0.0.1.dist-info/METADATA
osm_changeset_brain-0.0.1.dist-info/WHEEL
osm_changeset_brain-0.0.1.dist-info/top_level.txt
osm_changeset_brain-0.0.1.dist-info/RECORD
